bda.plone.shop-2.0b1-py3.9-nspkg.pth
bda/plone/shop/__init__.py
bda/plone/shop/behaviors.py
bda/plone/shop/cartdata.py
bda/plone/shop/checkout.py
bda/plone/shop/configure.zcml
bda/plone/shop/dx.py
bda/plone/shop/dx.zcml
bda/plone/shop/i18n.sh
bda/plone/shop/indexer.py
bda/plone/shop/interfaces.py
bda/plone/shop/mailnotify.py
bda/plone/shop/orders.py
bda/plone/shop/payment.py
bda/plone/shop/permissions.py
bda/plone/shop/permissions.zcml
bda/plone/shop/profiles.zcml
bda/plone/shop/setuphandlers.py
bda/plone/shop/shipping.py
bda/plone/shop/utils.py
bda/plone/shop/vocabularies.py
bda/plone/shop/vocabularies.zcml
bda/plone/shop/browser/__init__.py
bda/plone/shop/browser/actions.py
bda/plone/shop/browser/admin.pt
bda/plone/shop/browser/admin.py
bda/plone/shop/browser/availability.py
bda/plone/shop/browser/availability_details.pt
bda/plone/shop/browser/buyable.pt
bda/plone/shop/browser/buyable.py
bda/plone/shop/browser/buyable_viewlet.pt
bda/plone/shop/browser/configure.zcml
bda/plone/shop/browser/controlpanel.py
bda/plone/shop/browser/listing_summary.pt
bda/plone/shop/browser/navigation.py
bda/plone/shop/browser/shop.css
bda/plone/shop/browser/shop.css.map
bda/plone/shop/browser/toolbar.py
bda/plone/shop/browser/static/shop.css
bda/plone/shop/browser/static/shop.css.map
bda/plone/shop/browser/static/shop.js
bda/plone/shop/browser/static/shop.min.css
bda/plone/shop/locales/bda.plone.shop.pot
bda/plone/shop/locales/manual.pot
bda/plone/shop/locales/de/LC_MESSAGES/bda.plone.shop.po
bda/plone/shop/locales/en/LC_MESSAGES/bda.plone.shop.po
bda/plone/shop/locales/fr/LC_MESSAGES/bda.plone.shop.po
bda/plone/shop/locales/it/LC_MESSAGES/bda.plone.shop.po
bda/plone/shop/locales/nl/LC_MESSAGES/bda.plone.shop.po
bda/plone/shop/locales/nn/LC_MESSAGES/bda.plone.shop.po
bda/plone/shop/locales/no/LC_MESSAGES/bda.plone.shop.po
bda/plone/shop/profiles/default/actions.xml
bda/plone/shop/profiles/default/browserlayer.xml
bda/plone/shop/profiles/default/catalog.xml
bda.plone.shop-2.0b1.dist-info/LICENSE.rst
bda.plone.shop-2.0b1.dist-info/LICENSE_GPL.rst
bda.plone.shop-2.0b1.dist-info/METADATA
bda.plone.shop-2.0b1.dist-info/WHEEL
bda.plone.shop-2.0b1.dist-info/entry_points.txt
bda.plone.shop-2.0b1.dist-info/namespace_packages.txt
bda.plone.shop-2.0b1.dist-info/top_level.txt
bda.plone.shop-2.0b1.dist-info/RECORD
