Metadata-Version: 2.1
Name: bda.plone.shop
Version: 2.0b1
Summary: Shop Solution for Plone
Author: BlueDynamics Alliance
Author-email: dev@bluedynamics.com
License: GNU General Public Licence
Classifier: Framework :: Plone
Classifier: Framework :: Plone :: 6.0
Classifier: Framework :: Plone :: Addon
Classifier: Framework :: Zope
Classifier: Framework :: Zope :: 5
Classifier: License :: OSI Approved :: GNU General Public License (GPL)
Classifier: Programming Language :: Python
Classifier: Programming Language :: Python :: 3.7
Classifier: Programming Language :: Python :: 3.8
Classifier: Programming Language :: Python :: 3.9
Classifier: Programming Language :: Python :: 3.10
Classifier: Topic :: Software Development :: Libraries :: Python Modules
Requires-Python: >=3.7
License-File: LICENSE.rst
License-File: LICENSE_GPL.rst
Requires-Dist: bda.plone.discount
Requires-Dist: bda.plone.orders
Requires-Dist: collective.z3cform.datagridfield
Requires-Dist: Products.CMFPlone >=6.0a1
Requires-Dist: plone.api
Requires-Dist: setuptools
Requires-Dist: zope.deferredimport
Requires-Dist: zope.schema >=3.4
Provides-Extra: test
Requires-Dist: plone.app.contenttypes ; extra == 'test'
Requires-Dist: plone.app.dexterity ; extra == 'test'
Requires-Dist: plone.app.robotframework[debug] ; extra == 'test'
Requires-Dist: plone.app.testing[robot] ; extra == 'test'
Requires-Dist: Products.PrintingMailHost ; extra == 'test'
